bpe_summarizer.py
bpe_summarizer-0.2.1.dist-info/LICENSE
bpe_summarizer-0.2.1.dist-info/WHEEL
bpe_summarizer-0.2.1.dist-info/METADATA
bpe_summarizer-0.2.1.dist-info/RECORD
