Metadata-Version: 2.1
Name: bpe-summarizer
Version: 0.2.1
Summary: This summarizer attempts to leverage Byte Pair Encoding (BPE) tokenization and the Bart vocabulary to filter text by semantic meaningfulness.
Home-page: https://github.com/crodriguez1a/bpe-summarizer
License: MIT
Author: crodriguez1a
Author-email: crodriguez1a@gmail.com
Requires-Python: >=3.7,<4.0
Classifier: License :: OSI Approved :: MIT License
Classifier: Programming Language :: Python :: 3
Classifier: Programming Language :: Python :: 3.7
Classifier: Programming Language :: Python :: 3.8
Requires-Dist: nltk (>=3.5,<4.0)
Requires-Dist: scipy (>=1.4.1,<2.0.0)
Requires-Dist: transformers (>=2.11.0,<3.0.0)
Project-URL: Repository, https://github.com/crodriguez1a/bpe-summarizer
